cameo_youtube_transcript.py
cameo_youtube_transcript-1.1.1.dist-info/METADATA
cameo_youtube_transcript-1.1.1.dist-info/WHEEL
cameo_youtube_transcript-1.1.1.dist-info/entry_points.txt
cameo_youtube_transcript-1.1.1.dist-info/top_level.txt
cameo_youtube_transcript-1.1.1.dist-info/RECORD
