Metadata-Version: 2.4
Name: cameo-youtube-transcript
Version: 1.1.1
Summary: 一個用於下載 YouTube 影片字幕的工具
Home-page: https://github.com/bohachu/cameo_youtube_transcript
Author: Bowen Chiu
Author-email: cbh@cameo.tw
License: MIT
Keywords: youtube,transcript,subtitle,字幕,下載,cameo
Classifier: Programming Language :: Python :: 3
Classifier: License :: OSI Approved :: MIT License
Classifier: Operating System :: OS Independent
Classifier: Natural Language :: Chinese (Traditional)
Classifier: Topic :: Multimedia :: Video
Classifier: Topic :: Text Processing
Requires-Python: >=3.6
Requires-Dist: youtube_transcript_api==1.1.0
Dynamic: author
Dynamic: author-email
Dynamic: classifier
Dynamic: description
Dynamic: description-content-type
Dynamic: home-page
Dynamic: keywords
Dynamic: license
Dynamic: requires-dist
Dynamic: requires-python
Dynamic: summary
